[{"Date_Time": "2019-11-25T15:30:02.0000000Z", "Product_ID": "4010758692-PILOTB.upf", "User_Name": "FZ2-60B110$", "bicoe_load_dttm": "2019-11-25T20:38:04.081Z", "file_name": "twb-2002-100011-2019-11-25T20-37-32.328Z0000000000000404", "file_timestamp": "2019-11-25T20:37:32.3248957Z000000000000000", "hdfs_file_name": "pap_1574714280113", "location": "0,2,23", "tooltype": 889403487, "ulCornerToleranceFailure": 0, "ulPossibleMissing": 0, "ulPurged": 0, "ulRejects": 0, "ulVPSHeightFailure": 0, "ulVPSPartPresenceFailure": 0, "ulballcountfailure": 0, "ulcomplocationfailure": 0, "ulcompmissing": 0, "ulcompsizefailure": 0, "ulcompupsidedown": 0, "ulfeaturecountfailure": 0, "ulfeaturelocationfailure": 0, "ulfeaturespacingfailure": 0, "ulleadcountfailure": 0, "ulleaddeviationfailure": 0, "ulleadlocationfailure": 0, "ulleadspacingfailure": 0, "ulleadspanfailure": 0, "ulorientationcheckfailure": 0, "ulpicks": 121, "ulpitchfailure": 0, "ulplacements": 122, "xml_stat_cd": "192", "xml_tag_id": "100011", "xml_tag_nm": "oledbtag-mm-twb-gc10-nozzle"}, {"Date_Time": "2019-11-25T15:30:02.0000000Z", "Product_ID": "4010758692-PILOTB.upf", "User_Name": "FZ2-60B110$", "bicoe_load_dttm": "2019-11-25T20:38:04.081Z", "file_name": "twb-2002-100011-2019-11-25T20-37-32.328Z0000000000000404", "file_timestamp": "2019-11-25T20:37:32.3248957Z000000000000000", "hdfs_file_name": "pap_1574714280113", "location": "0,2,26", "tooltype": 889403487, "ulCornerToleranceFailure": 0, "ulPossibleMissing": 0, "ulPurged": 0, "ulRejects": 0, "ulVPSHeightFailure": 0, "ulVPSPartPresenceFailure": 0, "ulballcountfailure": 0, "ulcomplocationfailure": 0, "ulcompmissing": 0, "ulcompsizefailure": 0, "ulcompupsidedown": 0, "ulfeaturecountfailure": 0, "ulfeaturelocationfailure": 0, "ulfeaturespacingfailure": 0, "ulleadcountfailure": 0, "ulleaddeviationfailure": 0, "ulleadlocationfailure": 0, "ulleadspacingfailure": 0, "ulleadspanfailure": 0, "ulorientationcheckfailure": 0, "ulpicks": 121, "ulpitchfailure": 0, "ulplacements": 122, "xml_stat_cd": "192", "xml_tag_id": "100011", "xml_tag_nm": "oledbtag-mm-twb-gc10-nozzle"}, {"Date_Time": "2019-11-25T15:30:02.0000000Z", "Product_ID": "4010758692-PILOTB.upf", "User_Name": "FZ2-60B110$", "bicoe_load_dttm": "2019-11-25T20:38:04.081Z", "file_name": "twb-2002-100011-2019-11-25T20-37-32.328Z0000000000000404", "file_timestamp": "2019-11-25T20:37:32.3248957Z000000000000000", "hdfs_file_name": "pap_1574714280113", "location": "0,3,44", "tooltype": 839553155, "ulCornerToleranceFailure": 0, "ulPossibleMissing": 0, "ulPurged": 0, "ulRejects": 1, "ulVPSHeightFailure": 0, "ulVPSPartPresenceFailure": 0, "ulballcountfailure": 0, "ulcomplocationfailure": 0, "ulcompmissing": 1, "ulcompsizefailure": 0, "ulcompupsidedown": 0, "ulfeaturecountfailure": 0, "ulfeaturelocationfailure": 0, "ulfeaturespacingfailure": 0, "ulleadcountfailure": 0, "ulleaddeviationfailure": 0, "ulleadlocationfailure": 0, "ulleadspacingfailure": 0, "ulleadspanfailure": 0, "ulorientationcheckfailure": 0, "ulpicks": 108, "ulpitchfailure": 0, "ulplacements": 108, "xml_stat_cd": "192", "xml_tag_id": "100011", "xml_tag_nm": "oledbtag-mm-twb-gc10-nozzle"}, {"Date_Time": "2019-11-25T14:30:02.0000000Z", "Product_ID": "4010787715B.upf", "User_Name": "NAUSMEQSMTFPZ3$", "bicoe_load_dttm": "2019-11-25T20:38:04.093Z", "file_name": "twb-2002-100018-2019-11-25T20-37-32.919Z0000000000000407", "file_timestamp": "2019-11-25T20:37:32.9169515Z000000000000000", "hdfs_file_name": "pap_1574714280113", "location": "0,0,15", "tooltype": -2016171102, "ulCornerToleranceFailure": 0, "ulPossibleMissing": 0, "ulPurged": 0, "ulRejects": 0, "ulVPSHeightFailure": 0, "ulVPSPartPresenceFailure": 0, "ulballcountfailure": 0, "ulcomplocationfailure": 0, "ulcompmissing": 0, "ulcompsizefailure": 0, "ulcompupsidedown": 0, "ulfeaturecountfailure": 0, "ulfeaturelocationfailure": 0, "ulfeaturespacingfailure": 0, "ulleadcountfailure": 0, "ulleaddeviationfailure": 0, "ulleadlocationfailure": 0, "ulleadspacingfailure": 0, "ulleadspanfailure": 0, "ulorientationcheckfailure": 0, "ulpicks": 13, "ulpitchfailure": 0, "ulplacements": 13, "xml_stat_cd": "192", "xml_tag_id": "100018", "xml_tag_nm": "oledbtag-mm-meq-fpz3-nozzle"}, {"Date_Time": "2019-11-25T14:30:02.0000000Z", "Product_ID": "4010787715B.upf", "User_Name": "NAUSMEQSMTFPZ3$", "bicoe_load_dttm": "2019-11-25T20:38:04.093Z", "file_name": "twb-2002-100018-2019-11-25T20-37-32.919Z0000000000000407", "file_timestamp": "2019-11-25T20:37:32.9169515Z000000000000000", "hdfs_file_name": "pap_1574714280113", "location": "0,0,21", "tooltype": -779547612, "ulCornerToleranceFailure": 0, "ulPossibleMissing": 0, "ulPurged": 0, "ulRejects": 0, "ulVPSHeightFailure": 0, "ulVPSPartPresenceFailure": 0, "ulballcountfailure": 0, "ulcomplocationfailure": 0, "ulcompmissing": 0, "ulcompsizefailure": 0, "ulcompupsidedown": 0, "ulfeaturecountfailure": 0, "ulfeaturelocationfailure": 0, "ulfeaturespacingfailure": 0, "ulleadcountfailure": 0, "ulleaddeviationfailure": 0, "ulleadlocationfailure": 0, "ulleadspacingfailure": 0, "ulleadspanfailure": 0, "ulorientationcheckfailure": 0, "ulpicks": 75, "ulpitchfailure": 0, "ulplacements": 74, "xml_stat_cd": "192", "xml_tag_id": "100018", "xml_tag_nm": "oledbtag-mm-meq-fpz3-nozzle"}, {"Date_Time": "2019-11-25T14:30:02.0000000Z", "Product_ID": "4010787715B.upf", "User_Name": "NAUSMEQSMTFPZ3$", "bicoe_load_dttm": "2019-11-25T20:38:04.093Z", "file_name": "twb-2002-100018-2019-11-25T20-37-32.919Z0000000000000407", "file_timestamp": "2019-11-25T20:37:32.9169515Z000000000000000", "hdfs_file_name": "pap_1574714280113", "location": "0,2,10", "tooltype": 722575810, "ulCornerToleranceFailure": 0, "ulPossibleMissing": 0, "ulPurged": 0, "ulRejects": 0, "ulVPSHeightFailure": 0, "ulVPSPartPresenceFailure": 0, "ulballcountfailure": 0, "ulcomplocationfailure": 0, "ulcompmissing": 0, "ulcompsizefailure": 0, "ulcompupsidedown": 0, "ulfeaturecountfailure": 0, "ulfeaturelocationfailure": 0, "ulfeaturespacingfailure": 0, "ulleadcountfailure": 0, "ulleaddeviationfailure": 0, "ulleadlocationfailure": 0, "ulleadspacingfailure": 0, "ulleadspanfailure": 0, "ulorientationcheckfailure": 0, "ulpicks": 37, "ulpitchfailure": 0, "ulplacements": 37, "xml_stat_cd": "192", "xml_tag_id": "100018", "xml_tag_nm": "oledbtag-mm-meq-fpz3-nozzle"}, {"Date_Time": "2019-11-25T14:30:02.0000000Z", "Product_ID": "4010787715B.upf", "User_Name": "NAUSMEQSMTFPZ3$", "bicoe_load_dttm": "2019-11-25T20:38:04.093Z", "file_name": "twb-2002-100018-2019-11-25T20-37-32.919Z0000000000000407", "file_timestamp": "2019-11-25T20:37:32.9169515Z000000000000000", "hdfs_file_name": "pap_1574714280113", "location": "0,2,45", "tooltype": 839553155, "ulCornerToleranceFailure": 0, "ulPossibleMissing": 0, "ulPurged": 0, "ulRejects": 0, "ulVPSHeightFailure": 0, "ulVPSPartPresenceFailure": 0, "ulballcountfailure": 0, "ulcomplocationfailure": 0, "ulcompmissing": 0, "ulcompsizefailure": 0, "ulcompupsidedown": 0, "ulfeaturecountfailure": 0, "ulfeaturelocationfailure": 0, "ulfeaturespacingfailure": 0, "ulleadcountfailure": 0, "ulleaddeviationfailure": 0, "ulleadlocationfailure": 0, "ulleadspacingfailure": 0, "ulleadspanfailure": 0, "ulorientationcheckfailure": 0, "ulpicks": 37, "ulpitchfailure": 0, "ulplacements": 37, "xml_stat_cd": "192", "xml_tag_id": "100018", "xml_tag_nm": "oledbtag-mm-meq-fpz3-nozzle"}, {"Date_Time": "2019-11-25T14:30:02.0000000Z", "Product_ID": "4010787715B.upf", "User_Name": "NAUSMEQSMTFPZ3$", "bicoe_load_dttm": "2019-11-25T20:38:04.093Z", "file_name": "twb-2002-100018-2019-11-25T20-37-32.919Z0000000000000407", "file_timestamp": "2019-11-25T20:37:32.9169515Z000000000000000", "hdfs_file_name": "pap_1574714280113", "location": "0,2,51", "tooltype": 2102068804, "ulCornerToleranceFailure": 0, "ulPossibleMissing": 0, "ulPurged": 0, "ulRejects": 0, "ulVPSHeightFailure": 0, "ulVPSPartPresenceFailure": 0, "ulballcountfailure": 0, "ulcomplocationfailure": 0, "ulcompmissing": 0, "ulcompsizefailure": 0, "ulcompupsidedown": 0, "ulfeaturecountfailure": 0, "ulfeaturelocationfailure": 0, "ulfeaturespacingfailure": 0, "ulleadcountfailure": 0, "ulleaddeviationfailure": 0, "ulleadlocationfailure": 0, "ulleadspacingfailure": 0, "ulleadspanfailure": 0, "ulorientationcheckfailure": 0, "ulpicks": 62, "ulpitchfailure": 0, "ulplacements": 61, "xml_stat_cd": "192", "xml_tag_id": "100018", "xml_tag_nm": "oledbtag-mm-meq-fpz3-nozzle"}, {"Date_Time": "2019-11-25T14:30:02.0000000Z", "Product_ID": "4010787715B.upf", "User_Name": "NAUSMEQSMTFPZ3$", "bicoe_load_dttm": "2019-11-25T20:38:04.093Z", "file_name": "twb-2002-100018-2019-11-25T20-37-32.919Z0000000000000407", "file_timestamp": "2019-11-25T20:37:32.9169515Z000000000000000", "hdfs_file_name": "pap_1574714280113", "location": "0,2,54", "tooltype": 2102068804, "ulCornerToleranceFailure": 0, "ulPossibleMissing": 0, "ulPurged": 0, "ulRejects": 0, "ulVPSHeightFailure": 0, "ulVPSPartPresenceFailure": 0, "ulballcountfailure": 0, "ulcomplocationfailure": 0, "ulcompmissing": 0, "ulcompsizefailure": 0, "ulcompupsidedown": 0, "ulfeaturecountfailure": 0, "ulfeaturelocationfailure": 0, "ulfeaturespacingfailure": 0, "ulleadcountfailure": 0, "ulleaddeviationfailure": 0, "ulleadlocationfailure": 0, "ulleadspacingfailure": 0, "ulleadspanfailure": 0, "ulorientationcheckfailure": 0, "ulpicks": 50, "ulpitchfailure": 0, "ulplacements": 49, "xml_stat_cd": "192", "xml_tag_id": "100018", "xml_tag_nm": "oledbtag-mm-meq-fpz3-nozzle"}, {"Date_Time": "2019-11-25T14:30:02.0000000Z", "Product_ID": "4010787715B.upf", "User_Name": "NAUSMEQSMTFPZ3$", "bicoe_load_dttm": "2019-11-25T20:38:04.093Z", "file_name": "twb-2002-100018-2019-11-25T20-37-32.919Z0000000000000407", "file_timestamp": "2019-11-25T20:37:32.9169515Z000000000000000", "hdfs_file_name": "pap_1574714280113", "location": "0,2,57", "tooltype": 2102068804, "ulCornerToleranceFailure": 0, "ulPossibleMissing": 0, "ulPurged": 0, "ulRejects": 0, "ulVPSHeightFailure": 0, "ulVPSPartPresenceFailure": 0, "ulballcountfailure": 0, "ulcomplocationfailure": 0, "ulcompmissing": 0, "ulcompsizefailure": 0, "ulcompupsidedown": 0, "ulfeaturecountfailure": 0, "ulfeaturelocationfailure": 0, "ulfeaturespacingfailure": 0, "ulleadcountfailure": 0, "ulleaddeviationfailure": 0, "ulleadlocationfailure": 0, "ulleadspacingfailure": 0, "ulleadspanfailure": 0, "ulorientationcheckfailure": 0, "ulpicks": 49, "ulpitchfailure": 0, "ulplacements": 49, "xml_stat_cd": "192", "xml_tag_id": "100018", "xml_tag_nm": "oledbtag-mm-meq-fpz3-nozzle"}]