[{"Date_Time": "2019-11-25T22:30:02.0000000Z", "Product_ID": "4010722452B.upf", "User_Name": "FZ2-60B110$", "bicoe_load_dttm": "2019-11-26T03:42:34.093Z", "file_name": "twb-2002-100011-2019-11-26T03-42-12.896Z0000000000000213", "file_timestamp": "2019-11-26T03:42:12.8929725Z000000000000000", "hdfs_file_name": "pap_1574739750123", "location": "0,3,37", "tooltype": 839553155, "ulCornerToleranceFailure": 0, "ulPossibleMissing": 0, "ulPurged": 0, "ulRejects": 0, "ulVPSHeightFailure": 0, "ulVPSPartPresenceFailure": 0, "ulballcountfailure": 0, "ulcomplocationfailure": 0, "ulcompmissing": 0, "ulcompsizefailure": 0, "ulcompupsidedown": 0, "ulfeaturecountfailure": 0, "ulfeaturelocationfailure": 0, "ulfeaturespacingfailure": 0, "ulleadcountfailure": 0, "ulleaddeviationfailure": 0, "ulleadlocationfailure": 0, "ulleadspacingfailure": 0, "ulleadspanfailure": 0, "ulorientationcheckfailure": 0, "ulpicks": 62, "ulpitchfailure": 0, "ulplacements": 61, "xml_stat_cd": "192", "xml_tag_id": "100011", "xml_tag_nm": "oledbtag-mm-twb-gc10-nozzle"}, {"Date_Time": "2019-11-25T22:30:02.0000000Z", "Product_ID": "4010722452B.upf", "User_Name": "FZ2-60B110$", "bicoe_load_dttm": "2019-11-26T03:42:34.093Z", "file_name": "twb-2002-100011-2019-11-26T03-42-12.896Z0000000000000213", "file_timestamp": "2019-11-26T03:42:12.8929725Z000000000000000", "hdfs_file_name": "pap_1574739750123", "location": "0,3,40", "tooltype": 839553155, "ulCornerToleranceFailure": 0, "ulPossibleMissing": 0, "ulPurged": 0, "ulRejects": 0, "ulVPSHeightFailure": 0, "ulVPSPartPresenceFailure": 0, "ulballcountfailure": 0, "ulcomplocationfailure": 0, "ulcompmissing": 0, "ulcompsizefailure": 0, "ulcompupsidedown": 0, "ulfeaturecountfailure": 0, "ulfeaturelocationfailure": 0, "ulfeaturespacingfailure": 0, "ulleadcountfailure": 0, "ulleaddeviationfailure": 0, "ulleadlocationfailure": 0, "ulleadspacingfailure": 0, "ulleadspanfailure": 0, "ulorientationcheckfailure": 0, "ulpicks": 57, "ulpitchfailure": 0, "ulplacements": 56, "xml_stat_cd": "192", "xml_tag_id": "100011", "xml_tag_nm": "oledbtag-mm-twb-gc10-nozzle"}, {"Date_Time": "2019-11-25T22:30:02.0000000Z", "Product_ID": "4010722452B.upf", "User_Name": "FZ2-60B110$", "bicoe_load_dttm": "2019-11-26T03:42:34.093Z", "file_name": "twb-2002-100011-2019-11-26T03-42-12.896Z0000000000000213", "file_timestamp": "2019-11-26T03:42:12.8929725Z000000000000000", "hdfs_file_name": "pap_1574739750123", "location": "0,3,43", "tooltype": 839553155, "ulCornerToleranceFailure": 0, "ulPossibleMissing": 0, "ulPurged": 0, "ulRejects": 0, "ulVPSHeightFailure": 0, "ulVPSPartPresenceFailure": 0, "ulballcountfailure": 0, "ulcomplocationfailure": 0, "ulcompmissing": 0, "ulcompsizefailure": 0, "ulcompupsidedown": 0, "ulfeaturecountfailure": 0, "ulfeaturelocationfailure": 0, "ulfeaturespacingfailure": 0, "ulleadcountfailure": 0, "ulleaddeviationfailure": 0, "ulleadlocationfailure": 0, "ulleadspacingfailure": 0, "ulleadspanfailure": 0, "ulorientationcheckfailure": 0, "ulpicks": 57, "ulpitchfailure": 0, "ulplacements": 57, "xml_stat_cd": "192", "xml_tag_id": "100011", "xml_tag_nm": "oledbtag-mm-twb-gc10-nozzle"}, {"Date_Time": "2019-11-25T22:30:02.0000000Z", "Product_ID": "4010722452B.upf", "User_Name": "FZ2-60B110$", "bicoe_load_dttm": "2019-11-26T03:42:34.093Z", "file_name": "twb-2002-100011-2019-11-26T03-42-12.896Z0000000000000213", "file_timestamp": "2019-11-26T03:42:12.8929725Z000000000000000", "hdfs_file_name": "pap_1574739750123", "location": "0,3,46", "tooltype": 839553155, "ulCornerToleranceFailure": 0, "ulPossibleMissing": 0, "ulPurged": 0, "ulRejects": 0, "ulVPSHeightFailure": 0, "ulVPSPartPresenceFailure": 0, "ulballcountfailure": 0, "ulcomplocationfailure": 0, "ulcompmissing": 0, "ulcompsizefailure": 0, "ulcompupsidedown": 0, "ulfeaturecountfailure": 0, "ulfeaturelocationfailure": 0, "ulfeaturespacingfailure": 0, "ulleadcountfailure": 0, "ulleaddeviationfailure": 0, "ulleadlocationfailure": 0, "ulleadspacingfailure": 0, "ulleadspanfailure": 0, "ulorientationcheckfailure": 0, "ulpicks": 57, "ulpitchfailure": 0, "ulplacements": 56, "xml_stat_cd": "192", "xml_tag_id": "100011", "xml_tag_nm": "oledbtag-mm-twb-gc10-nozzle"}, {"Date_Time": "2019-11-25T22:15:02.0000000Z", "Product_ID": "4010819440T.upf", "User_Name": "4990F044$", "bicoe_load_dttm": "2019-11-26T03:43:00.177Z", "file_name": "twb-2002-100016-2019-11-26T03-42-56.502Z0000000000000229", "file_timestamp": "2019-11-26T03:42:56.5015277Z000000000000000", "hdfs_file_name": "pap_1574739780085", "location": "0,0,2", "tooltype": 889403487, "ulCornerToleranceFailure": 0, "ulPossibleMissing": 0, "ulPurged": 0, "ulRejects": 0, "ulVPSHeightFailure": 0, "ulVPSPartPresenceFailure": 0, "ulballcountfailure": 0, "ulcomplocationfailure": 0, "ulcompmissing": 0, "ulcompsizefailure": 0, "ulcompupsidedown": 0, "ulfeaturecountfailure": 0, "ulfeaturelocationfailure": 0, "ulfeaturespacingfailure": 0, "ulleadcountfailure": 0, "ulleaddeviationfailure": 0, "ulleadlocationfailure": 0, "ulleadspacingfailure": 0, "ulleadspanfailure": 0, "ulorientationcheckfailure": 0, "ulpicks": 7, "ulpitchfailure": 0, "ulplacements": 7, "xml_stat_cd": "192", "xml_tag_id": "100016", "xml_tag_nm": "oledbtag-mm-mmc-gc6-nozzle"}, {"Date_Time": "2019-11-25T22:15:02.0000000Z", "Product_ID": "4010819440T.upf", "User_Name": "4990F044$", "bicoe_load_dttm": "2019-11-26T03:43:00.177Z", "file_name": "twb-2002-100016-2019-11-26T03-42-56.502Z0000000000000229", "file_timestamp": "2019-11-26T03:42:56.5015277Z000000000000000", "hdfs_file_name": "pap_1574739780085", "location": "0,0,5", "tooltype": 889403487, "ulCornerToleranceFailure": 0, "ulPossibleMissing": 0, "ulPurged": 0, "ulRejects": 0, "ulVPSHeightFailure": 0, "ulVPSPartPresenceFailure": 0, "ulballcountfailure": 0, "ulcomplocationfailure": 0, "ulcompmissing": 0, "ulcompsizefailure": 0, "ulcompupsidedown": 0, "ulfeaturecountfailure": 0, "ulfeaturelocationfailure": 0, "ulfeaturespacingfailure": 0, "ulleadcountfailure": 0, "ulleaddeviationfailure": 0, "ulleadlocationfailure": 0, "ulleadspacingfailure": 0, "ulleadspanfailure": 0, "ulorientationcheckfailure": 0, "ulpicks": 7, "ulpitchfailure": 0, "ulplacements": 7, "xml_stat_cd": "192", "xml_tag_id": "100016", "xml_tag_nm": "oledbtag-mm-mmc-gc6-nozzle"}, {"Date_Time": "2019-11-25T22:15:02.0000000Z", "Product_ID": "4010819440T.upf", "User_Name": "4990F044$", "bicoe_load_dttm": "2019-11-26T03:43:00.177Z", "file_name": "twb-2002-100016-2019-11-26T03-42-56.502Z0000000000000229", "file_timestamp": "2019-11-26T03:42:56.5015277Z000000000000000", "hdfs_file_name": "pap_1574739780085", "location": "0,0,8", "tooltype": 889403487, "ulCornerToleranceFailure": 0, "ulPossibleMissing": 0, "ulPurged": 0, "ulRejects": 0, "ulVPSHeightFailure": 0, "ulVPSPartPresenceFailure": 0, "ulballcountfailure": 0, "ulcomplocationfailure": 0, "ulcompmissing": 0, "ulcompsizefailure": 0, "ulcompupsidedown": 0, "ulfeaturecountfailure": 0, "ulfeaturelocationfailure": 0, "ulfeaturespacingfailure": 0, "ulleadcountfailure": 0, "ulleaddeviationfailure": 0, "ulleadlocationfailure": 0, "ulleadspacingfailure": 0, "ulleadspanfailure": 0, "ulorientationcheckfailure": 0, "ulpicks": 7, "ulpitchfailure": 0, "ulplacements": 7, "xml_stat_cd": "192", "xml_tag_id": "100016", "xml_tag_nm": "oledbtag-mm-mmc-gc6-nozzle"}, {"Date_Time": "2019-11-25T22:15:02.0000000Z", "Product_ID": "4010819440T.upf", "User_Name": "4990F044$", "bicoe_load_dttm": "2019-11-26T03:43:00.177Z", "file_name": "twb-2002-100016-2019-11-26T03-42-56.502Z0000000000000229", "file_timestamp": "2019-11-26T03:42:56.5015277Z000000000000000", "hdfs_file_name": "pap_1574739780085", "location": "0,0,11", "tooltype": 889403487, "ulCornerToleranceFailure": 0, "ulPossibleMissing": 0, "ulPurged": 0, "ulRejects": 0, "ulVPSHeightFailure": 0, "ulVPSPartPresenceFailure": 0, "ulballcountfailure": 0, "ulcomplocationfailure": 0, "ulcompmissing": 0, "ulcompsizefailure": 0, "ulcompupsidedown": 0, "ulfeaturecountfailure": 0, "ulfeaturelocationfailure": 0, "ulfeaturespacingfailure": 0, "ulleadcountfailure": 0, "ulleaddeviationfailure": 0, "ulleadlocationfailure": 0, "ulleadspacingfailure": 0, "ulleadspanfailure": 0, "ulorientationcheckfailure": 0, "ulpicks": 7, "ulpitchfailure": 0, "ulplacements": 7, "xml_stat_cd": "192", "xml_tag_id": "100016", "xml_tag_nm": "oledbtag-mm-mmc-gc6-nozzle"}, {"Date_Time": "2019-11-25T22:15:02.0000000Z", "Product_ID": "4010819440T.upf", "User_Name": "4990F044$", "bicoe_load_dttm": "2019-11-26T03:43:00.177Z", "file_name": "twb-2002-100016-2019-11-26T03-42-56.502Z0000000000000229", "file_timestamp": "2019-11-26T03:42:56.5015277Z000000000000000", "hdfs_file_name": "pap_1574739780085", "location": "0,0,14", "tooltype": 889403487, "ulCornerToleranceFailure": 0, "ulPossibleMissing": 0, "ulPurged": 0, "ulRejects": 0, "ulVPSHeightFailure": 0, "ulVPSPartPresenceFailure": 0, "ulballcountfailure": 0, "ulcomplocationfailure": 0, "ulcompmissing": 0, "ulcompsizefailure": 0, "ulcompupsidedown": 0, "ulfeaturecountfailure": 0, "ulfeaturelocationfailure": 0, "ulfeaturespacingfailure": 0, "ulleadcountfailure": 0, "ulleaddeviationfailure": 0, "ulleadlocationfailure": 0, "ulleadspacingfailure": 0, "ulleadspanfailure": 0, "ulorientationcheckfailure": 0, "ulpicks": 7, "ulpitchfailure": 0, "ulplacements": 7, "xml_stat_cd": "192", "xml_tag_id": "100016", "xml_tag_nm": "oledbtag-mm-mmc-gc6-nozzle"}, {"Date_Time": "2019-11-25T22:15:02.0000000Z", "Product_ID": "4010819440T.upf", "User_Name": "4990F044$", "bicoe_load_dttm": "2019-11-26T03:43:00.177Z", "file_name": "twb-2002-100016-2019-11-26T03-42-56.502Z0000000000000229", "file_timestamp": "2019-11-26T03:42:56.5015277Z000000000000000", "hdfs_file_name": "pap_1574739780085", "location": "0,0,51", "tooltype": 1682978565, "ulCornerToleranceFailure": 0, "ulPossibleMissing": 0, "ulPurged": 0, "ulRejects": 0, "ulVPSHeightFailure": 0, "ulVPSPartPresenceFailure": 0, "ulballcountfailure": 0, "ulcomplocationfailure": 0, "ulcompmissing": 0, "ulcompsizefailure": 0, "ulcompupsidedown": 0, "ulfeaturecountfailure": 0, "ulfeaturelocationfailure": 0, "ulfeaturespacingfailure": 0, "ulleadcountfailure": 0, "ulleaddeviationfailure": 0, "ulleadlocationfailure": 0, "ulleadspacingfailure": 0, "ulleadspanfailure": 0, "ulorientationcheckfailure": 0, "ulpicks": 13, "ulpitchfailure": 0, "ulplacements": 13, "xml_stat_cd": "192", "xml_tag_id": "100016", "xml_tag_nm": "oledbtag-mm-mmc-gc6-nozzle"}]