[{"Date_Time": "2019-11-25T13:00:02.0000000Z", "Product_ID": "4010838785T.upf", "User_Name": "FZ2-60B014$", "bicoe_load_dttm": "2019-11-25T19:46:30.145Z", "file_name": "twb-2002-100016-2019-11-25T19-46-26.598Z0000000000000092", "file_timestamp": "2019-11-25T19:46:26.5925109Z000000000000000", "hdfs_file_name": "pap_1574711190108", "location": "0,0,30", "tooltype": 889403487, "ulCornerToleranceFailure": 0, "ulPossibleMissing": 0, "ulPurged": 0, "ulRejects": 0, "ulVPSHeightFailure": 0, "ulVPSPartPresenceFailure": 0, "ulballcountfailure": 0, "ulcomplocationfailure": 0, "ulcompmissing": 0, "ulcompsizefailure": 0, "ulcompupsidedown": 0, "ulfeaturecountfailure": 0, "ulfeaturelocationfailure": 0, "ulfeaturespacingfailure": 0, "ulleadcountfailure": 0, "ulleaddeviationfailure": 0, "ulleadlocationfailure": 0, "ulleadspacingfailure": 0, "ulleadspanfailure": 0, "ulorientationcheckfailure": 0, "ulpicks": 21, "ulpitchfailure": 0, "ulplacements": 22, "xml_stat_cd": "192", "xml_tag_id": "100016", "xml_tag_nm": "oledbtag-mm-mmc-gc2-nozzle"}, {"Date_Time": "2019-11-25T13:00:02.0000000Z", "Product_ID": "4010838785T.upf", "User_Name": "FZ2-60B014$", "bicoe_load_dttm": "2019-11-25T19:46:30.145Z", "file_name": "twb-2002-100016-2019-11-25T19-46-26.598Z0000000000000092", "file_timestamp": "2019-11-25T19:46:26.5925109Z000000000000000", "hdfs_file_name": "pap_1574711190108", "location": "0,0,33", "tooltype": 889403487, "ulCornerToleranceFailure": 0, "ulPossibleMissing": 0, "ulPurged": 0, "ulRejects": 0, "ulVPSHeightFailure": 0, "ulVPSPartPresenceFailure": 0, "ulballcountfailure": 0, "ulcomplocationfailure": 0, "ulcompmissing": 0, "ulcompsizefailure": 0, "ulcompupsidedown": 0, "ulfeaturecountfailure": 0, "ulfeaturelocationfailure": 0, "ulfeaturespacingfailure": 0, "ulleadcountfailure": 0, "ulleaddeviationfailure": 0, "ulleadlocationfailure": 0, "ulleadspacingfailure": 0, "ulleadspanfailure": 0, "ulorientationcheckfailure": 0, "ulpicks": 21, "ulpitchfailure": 0, "ulplacements": 22, "xml_stat_cd": "192", "xml_tag_id": "100016", "xml_tag_nm": "oledbtag-mm-mmc-gc2-nozzle"}, {"Date_Time": "2019-11-25T13:00:02.0000000Z", "Product_ID": "4010838785T.upf", "User_Name": "FZ2-60B014$", "bicoe_load_dttm": "2019-11-25T19:46:30.145Z", "file_name": "twb-2002-100016-2019-11-25T19-46-26.598Z0000000000000092", "file_timestamp": "2019-11-25T19:46:26.5925109Z000000000000000", "hdfs_file_name": "pap_1574711190108", "location": "0,0,36", "tooltype": 889403487, "ulCornerToleranceFailure": 0, "ulPossibleMissing": 0, "ulPurged": 0, "ulRejects": 0, "ulVPSHeightFailure": 0, "ulVPSPartPresenceFailure": 0, "ulballcountfailure": 0, "ulcomplocationfailure": 0, "ulcompmissing": 0, "ulcompsizefailure": 0, "ulcompupsidedown": 0, "ulfeaturecountfailure": 0, "ulfeaturelocationfailure": 0, "ulfeaturespacingfailure": 0, "ulleadcountfailure": 0, "ulleaddeviationfailure": 0, "ulleadlocationfailure": 0, "ulleadspacingfailure": 0, "ulleadspanfailure": 0, "ulorientationcheckfailure": 0, "ulpicks": 21, "ulpitchfailure": 0, "ulplacements": 22, "xml_stat_cd": "192", "xml_tag_id": "100016", "xml_tag_nm": "oledbtag-mm-mmc-gc2-nozzle"}, {"Date_Time": "2019-11-25T13:00:02.0000000Z", "Product_ID": "4010838785T.upf", "User_Name": "FZ2-60B014$", "bicoe_load_dttm": "2019-11-25T19:46:30.145Z", "file_name": "twb-2002-100016-2019-11-25T19-46-26.598Z0000000000000092", "file_timestamp": "2019-11-25T19:46:26.5925109Z000000000000000", "hdfs_file_name": "pap_1574711190108", "location": "0,1,2", "tooltype": 2102068804, "ulCornerToleranceFailure": 0, "ulPossibleMissing": 0, "ulPurged": 0, "ulRejects": 2, "ulVPSHeightFailure": 0, "ulVPSPartPresenceFailure": 0, "ulballcountfailure": 0, "ulcomplocationfailure": 0, "ulcompmissing": 2, "ulcompsizefailure": 0, "ulcompupsidedown": 0, "ulfeaturecountfailure": 0, "ulfeaturelocationfailure": 0, "ulfeaturespacingfailure": 0, "ulleadcountfailure": 0, "ulleaddeviationfailure": 0, "ulleadlocationfailure": 0, "ulleadspacingfailure": 0, "ulleadspanfailure": 0, "ulorientationcheckfailure": 0, "ulpicks": 45, "ulpitchfailure": 0, "ulplacements": 44, "xml_stat_cd": "192", "xml_tag_id": "100016", "xml_tag_nm": "oledbtag-mm-mmc-gc2-nozzle"}, {"Date_Time": "2019-11-25T13:00:02.0000000Z", "Product_ID": "4010838785T.upf", "User_Name": "FZ2-60B014$", "bicoe_load_dttm": "2019-11-25T19:46:30.145Z", "file_name": "twb-2002-100016-2019-11-25T19-46-26.598Z0000000000000092", "file_timestamp": "2019-11-25T19:46:26.5925109Z000000000000000", "hdfs_file_name": "pap_1574711190108", "location": "0,1,31", "tooltype": 1704090930, "ulCornerToleranceFailure": 0, "ulPossibleMissing": 0, "ulPurged": 0, "ulRejects": 1, "ulVPSHeightFailure": 0, "ulVPSPartPresenceFailure": 0, "ulballcountfailure": 0, "ulcomplocationfailure": 0, "ulcompmissing": 1, "ulcompsizefailure": 0, "ulcompupsidedown": 0, "ulfeaturecountfailure": 0, "ulfeaturelocationfailure": 0, "ulfeaturespacingfailure": 0, "ulleadcountfailure": 0, "ulleaddeviationfailure": 0, "ulleadlocationfailure": 0, "ulleadspacingfailure": 0, "ulleadspanfailure": 0, "ulorientationcheckfailure": 0, "ulpicks": 43, "ulpitchfailure": 0, "ulplacements": 43, "xml_stat_cd": "192", "xml_tag_id": "100016", "xml_tag_nm": "oledbtag-mm-mmc-gc2-nozzle"}, {"Date_Time": "2019-11-25T13:00:02.0000000Z", "Product_ID": "4010838785T.upf", "User_Name": "FZ2-60B014$", "bicoe_load_dttm": "2019-11-25T19:46:30.145Z", "file_name": "twb-2002-100016-2019-11-25T19-46-26.598Z0000000000000092", "file_timestamp": "2019-11-25T19:46:26.5925109Z000000000000000", "hdfs_file_name": "pap_1574711190108", "location": "0,1,35", "tooltype": 1704090930, "ulCornerToleranceFailure": 0, "ulPossibleMissing": 0, "ulPurged": 0, "ulRejects": 0, "ulVPSHeightFailure": 0, "ulVPSPartPresenceFailure": 0, "ulballcountfailure": 0, "ulcomplocationfailure": 0, "ulcompmissing": 0, "ulcompsizefailure": 0, "ulcompupsidedown": 0, "ulfeaturecountfailure": 0, "ulfeaturelocationfailure": 0, "ulfeaturespacingfailure": 0, "ulleadcountfailure": 0, "ulleaddeviationfailure": 0, "ulleadlocationfailure": 0, "ulleadspacingfailure": 0, "ulleadspanfailure": 0, "ulorientationcheckfailure": 0, "ulpicks": 43, "ulpitchfailure": 0, "ulplacements": 44, "xml_stat_cd": "192", "xml_tag_id": "100016", "xml_tag_nm": "oledbtag-mm-mmc-gc2-nozzle"}, {"Date_Time": "2019-11-25T13:00:02.0000000Z", "Product_ID": "4010838785T.upf", "User_Name": "FZ2-60B014$", "bicoe_load_dttm": "2019-11-25T19:46:30.145Z", "file_name": "twb-2002-100016-2019-11-25T19-46-26.598Z0000000000000092", "file_timestamp": "2019-11-25T19:46:26.5925109Z000000000000000", "hdfs_file_name": "pap_1574711190108", "location": "0,1,39", "tooltype": 1704090930, "ulCornerToleranceFailure": 0, "ulPossibleMissing": 0, "ulPurged": 0, "ulRejects": 0, "ulVPSHeightFailure": 0, "ulVPSPartPresenceFailure": 0, "ulballcountfailure": 0, "ulcomplocationfailure": 0, "ulcompmissing": 0, "ulcompsizefailure": 0, "ulcompupsidedown": 0, "ulfeaturecountfailure": 0, "ulfeaturelocationfailure": 0, "ulfeaturespacingfailure": 0, "ulleadcountfailure": 0, "ulleaddeviationfailure": 0, "ulleadlocationfailure": 0, "ulleadspacingfailure": 0, "ulleadspanfailure": 0, "ulorientationcheckfailure": 0, "ulpicks": 43, "ulpitchfailure": 0, "ulplacements": 44, "xml_stat_cd": "192", "xml_tag_id": "100016", "xml_tag_nm": "oledbtag-mm-mmc-gc2-nozzle"}, {"Date_Time": "2019-11-25T13:00:02.0000000Z", "Product_ID": "4010838785T.upf", "User_Name": "FZ2-60B014$", "bicoe_load_dttm": "2019-11-25T19:46:30.145Z", "file_name": "twb-2002-100016-2019-11-25T19-46-26.598Z0000000000000092", "file_timestamp": "2019-11-25T19:46:26.5925109Z000000000000000", "hdfs_file_name": "pap_1574711190108", "location": "0,2,51", "tooltype": 839553155, "ulCornerToleranceFailure": 0, "ulPossibleMissing": 0, "ulPurged": 0, "ulRejects": 0, "ulVPSHeightFailure": 0, "ulVPSPartPresenceFailure": 0, "ulballcountfailure": 0, "ulcomplocationfailure": 0, "ulcompmissing": 0, "ulcompsizefailure": 0, "ulcompupsidedown": 0, "ulfeaturecountfailure": 0, "ulfeaturelocationfailure": 0, "ulfeaturespacingfailure": 0, "ulleadcountfailure": 0, "ulleaddeviationfailure": 0, "ulleadlocationfailure": 0, "ulleadspacingfailure": 0, "ulleadspanfailure": 0, "ulorientationcheckfailure": 0, "ulpicks": 21, "ulpitchfailure": 0, "ulplacements": 21, "xml_stat_cd": "192", "xml_tag_id": "100016", "xml_tag_nm": "oledbtag-mm-mmc-gc2-nozzle"}, {"Date_Time": "2019-11-25T13:00:02.0000000Z", "Product_ID": "4010838785T.upf", "User_Name": "FZ2-60B014$", "bicoe_load_dttm": "2019-11-25T19:46:30.145Z", "file_name": "twb-2002-100016-2019-11-25T19-46-26.598Z0000000000000092", "file_timestamp": "2019-11-25T19:46:26.5925109Z000000000000000", "hdfs_file_name": "pap_1574711190108", "location": "0,3,35", "tooltype": 1704090930, "ulCornerToleranceFailure": 0, "ulPossibleMissing": 0, "ulPurged": 0, "ulRejects": 0, "ulVPSHeightFailure": 0, "ulVPSPartPresenceFailure": 0, "ulballcountfailure": 0, "ulcomplocationfailure": 0, "ulcompmissing": 0, "ulcompsizefailure": 0, "ulcompupsidedown": 0, "ulfeaturecountfailure": 0, "ulfeaturelocationfailure": 0, "ulfeaturespacingfailure": 0, "ulleadcountfailure": 0, "ulleaddeviationfailure": 0, "ulleadlocationfailure": 0, "ulleadspacingfailure": 0, "ulleadspanfailure": 0, "ulorientationcheckfailure": 0, "ulpicks": 21, "ulpitchfailure": 0, "ulplacements": 21, "xml_stat_cd": "192", "xml_tag_id": "100016", "xml_tag_nm": "oledbtag-mm-mmc-gc2-nozzle"}, {"Date_Time": "2019-11-25T13:00:02.0000000Z", "Product_ID": "4010838785T.upf", "User_Name": "FZ2-60B014$", "bicoe_load_dttm": "2019-11-25T19:46:30.145Z", "file_name": "twb-2002-100016-2019-11-25T19-46-26.598Z0000000000000092", "file_timestamp": "2019-11-25T19:46:26.5925109Z000000000000000", "hdfs_file_name": "pap_1574711190108", "location": "0,3,38", "tooltype": 1704090930, "ulCornerToleranceFailure": 0, "ulPossibleMissing": 0, "ulPurged": 0, "ulRejects": 0, "ulVPSHeightFailure": 0, "ulVPSPartPresenceFailure": 0, "ulballcountfailure": 0, "ulcomplocationfailure": 0, "ulcompmissing": 0, "ulcompsizefailure": 0, "ulcompupsidedown": 0, "ulfeaturecountfailure": 0, "ulfeaturelocationfailure": 0, "ulfeaturespacingfailure": 0, "ulleadcountfailure": 0, "ulleaddeviationfailure": 0, "ulleadlocationfailure": 0, "ulleadspacingfailure": 0, "ulleadspanfailure": 0, "ulorientationcheckfailure": 0, "ulpicks": 21, "ulpitchfailure": 0, "ulplacements": 21, "xml_stat_cd": "192", "xml_tag_id": "100016", "xml_tag_nm": "oledbtag-mm-mmc-gc2-nozzle"}]